{
  "prices": {
    "bitcoin": {
      "usd": 75543,
      "usd_24h_change": -0.7144,
      "usd_market_cap": 1512940648085,
      "usd_24h_vol": 42363174159
    },
    "eigenlayer": {
      "usd": 0.179126,
      "usd_24h_change": -2.18362,
      "usd_market_cap": 124067748,
      "usd_24h_vol": 17529460
    },
    "unibase": {
      "usd": 0.04788264,
      "usd_24h_change": 18.74941,
      "usd_market_cap": 120146453,
      "usd_24h_vol": 7420598
    },
    "concordium": {
      "usd": 0.00480412,
      "usd_24h_change": -0.77923,
      "usd_market_cap": 57797837,
      "usd_24h_vol": 416458
    },
    "skale": {
      "usd": 0.00708915,
      "usd_24h_change": -1.82379,
      "usd_market_cap": 43205912,
      "usd_24h_vol": 4453467
    },
    "peaq-2": {
      "usd": 0.01609164,
      "usd_24h_change": -2.60817,
      "usd_market_cap": 32859160,
      "usd_24h_vol": 1116231
    },
    "bankercoin-2": {
      "usd": 0.00032432,
      "usd_24h_change": -4.2651,
      "usd_market_cap": 32433691,
      "usd_24h_vol": 3680896
    },
    "amiko": {
      "usd": 0.03484561,
      "usd_24h_change": -5.43981,
      "usd_market_cap": 27575777,
      "usd_24h_vol": 496835
    },
    "flock-2": {
      "usd": 0.062925,
      "usd_24h_change": 4.60288,
      "usd_market_cap": 21617343,
      "usd_24h_vol": 17579688
    },
    "magic": {
      "usd": 0.064,
      "usd_24h_change": -2.74387,
      "usd_market_cap": 20989985,
      "usd_24h_vol": 4718500
    },
    "elsa": {
      "usd": 0.066949,
      "usd_24h_change": -2.01343,
      "usd_market_cap": 15340684,
      "usd_24h_vol": 3262047
    },
    "openserv": {
      "usd": 0.01802472,
      "usd_24h_change": -8.21813,
      "usd_market_cap": 13520013,
      "usd_24h_vol": 3833880
    },
    "autonolas": {
      "usd": 0.04101631,
      "usd_24h_change": -1.46204,
      "usd_market_cap": 9707180,
      "usd_24h_vol": 164305
    },
    "anyspend": {
      "usd": 0.03439279,
      "usd_24h_change": -0.60968,
      "usd_market_cap": 7566415,
      "usd_24h_vol": 45.39
    },
    "zauthx402": {
      "usd": 0.0039911,
      "usd_24h_change": -0.2217,
      "usd_market_cap": 3791402,
      "usd_24h_vol": 65838
    },
    "daydreams": {
      "usd": 0.00440241,
      "usd_24h_change": -2.54423,
      "usd_market_cap": 3736568,
      "usd_24h_vol": 816468
    },
    "payai-network-2": {
      "usd": 0.00320208,
      "usd_24h_change": 11.06398,
      "usd_market_cap": 3352955,
      "usd_24h_vol": 2569912
    },
    "coral-protocol": {
      "usd": 0.00023942,
      "usd_24h_change": -1.37737,
      "usd_market_cap": 2389470,
      "usd_24h_vol": 254722
    },
    "cod3x": {
      "usd": 0.04227954,
      "usd_24h_change": 1.92763,
      "usd_market_cap": 2068212,
      "usd_24h_vol": 1823.46
    },
    "ping": {
      "usd": 0.00166046,
      "usd_24h_change": 4.58564,
      "usd_market_cap": 1660456,
      "usd_24h_vol": 2321962
    },
    "aubrai-by-bio": {
      "usd": 1.13,
      "usd_24h_change": 5.92371,
      "usd_market_cap": 1554859,
      "usd_24h_vol": 7064.39
    },
    "alphakek-ai": {
      "usd": 0.004477,
      "usd_24h_change": -0.61341,
      "usd_market_cap": 1062374,
      "usd_24h_vol": 4666.23
    },
    "homebrew-robotics-club": {
      "usd": 0.00122569,
      "usd_24h_change": 5.12805,
      "usd_market_cap": 1026162,
      "usd_24h_vol": 8066.92
    },
    "ethy-ai": {
      "usd": 0.00104832,
      "usd_24h_change": -8.79701,
      "usd_market_cap": 954859,
      "usd_24h_vol": 39427
    },
    "santa-by-virtuals": {
      "usd": 0.00094321,
      "usd_24h_change": 2.13242,
      "usd_market_cap": 944167,
      "usd_24h_vol": 12332.13
    },
    "heurist": {
      "usd": 0.00444233,
      "usd_24h_change": -3.80911,
      "usd_market_cap": 877405,
      "usd_24h_vol": 217736
    },
    "dexter-ai": {
      "usd": 0.00086668,
      "usd_24h_change": -16.37078,
      "usd_market_cap": 866599,
      "usd_24h_vol": 52934
    },
    "0xgasless-2": {
      "usd": 0.057686,
      "usd_24h_change": -1.26262,
      "usd_market_cap": 634399,
      "usd_24h_vol": 213.65
    },
    "switchboard": {
      "usd": 0.00312918,
      "usd_24h_change": 5.71735,
      "usd_market_cap": 500629,
      "usd_24h_vol": 1771030
    },
    "sally-a1c": {
      "usd": 0.02376033,
      "usd_24h_change": -1.12224,
      "usd_market_cap": 499473,
      "usd_24h_vol": 35.74
    },
    "the-swarm": {
      "usd": 0.00095331,
      "usd_24h_change": 0.8773,
      "usd_market_cap": 497709,
      "usd_24h_vol": 650.31
    },
    "otto-ai": {
      "usd": 0.00106078,
      "usd_24h_change": -6.58235,
      "usd_market_cap": 484831,
      "usd_24h_vol": 4139.03
    },
    "orbofi-ai": {
      "usd": 0.00032063,
      "usd_24h_change": -12.78927,
      "usd_market_cap": 482266,
      "usd_24h_vol": 40062
    },
    "gloria-ai": {
      "usd": 0.00055271,
      "usd_24h_change": -0.51898,
      "usd_market_cap": 437198,
      "usd_24h_vol": 177.04
    },
    "prxvt-by-virtuals": {
      "usd": 0.00065642,
      "usd_24h_change": 3.78145,
      "usd_market_cap": 409582,
      "usd_24h_vol": 2630.14
    },
    "neurobro": {
      "usd": 0.0004748,
      "usd_24h_change": -4.00832,
      "usd_market_cap": 379600,
      "usd_24h_vol": 1318.88
    },
    "ace-data-cloud-2": {
      "usd": 0.00036492,
      "usd_24h_change": 5.11157,
      "usd_market_cap": 364921,
      "usd_24h_vol": 2435.43
    },
    "capminal": {
      "usd": 0.00051866,
      "usd_24h_change": -2.00249,
      "usd_market_cap": 304814,
      "usd_24h_vol": 1633.36
    },
    "smolcoin-2": {
      "usd": 0.00034372,
      "usd_24h_change": null,
      "usd_market_cap": 289720,
      "usd_24h_vol": 172.37
    },
    "trackgood-ai": {
      "usd": 0.00027979,
      "usd_24h_change": -0.85381,
      "usd_market_cap": 280056,
      "usd_24h_vol": 142.04
    },
    "zara-ai": {
      "usd": 0.00041166,
      "usd_24h_change": -0.89744,
      "usd_market_cap": 257446,
      "usd_24h_vol": 49416
    },
    "wachxbt": {
      "usd": 0.00037443,
      "usd_24h_change": -6.73383,
      "usd_market_cap": 239894,
      "usd_24h_vol": 3375.35
    },
    "mio": {
      "usd": 0.00022124,
      "usd_24h_change": -3.15062,
      "usd_market_cap": 221242,
      "usd_24h_vol": 4.48
    },
    "praxis": {
      "usd": 0.00212756,
      "usd_24h_change": -8.95954,
      "usd_market_cap": 212756,
      "usd_24h_vol": 2373.51
    },
    "xona-agent": {
      "usd": 0.00020778,
      "usd_24h_change": -8.88043,
      "usd_market_cap": 200626,
      "usd_24h_vol": 4168.75
    },
    "eliza": {
      "usd": 0.00019884,
      "usd_24h_change": -1.24668,
      "usd_market_cap": 197729,
      "usd_24h_vol": 887.51
    },
    "regent-2": {
      "usd": 0.00000969,
      "usd_24h_change": -0.04645,
      "usd_market_cap": 193837,
      "usd_24h_vol": 49.58
    },
    "kilt-protocol-3": {
      "usd": 0.00065592,
      "usd_24h_change": 3.62578,
      "usd_market_cap": 191944,
      "usd_24h_vol": 2364.57
    },
    "hey-lol": {
      "usd": 0.00046591,
      "usd_24h_change": -5.95773,
      "usd_market_cap": 190065,
      "usd_24h_vol": 4278.14
    },
    "token-metrics-ai": {
      "usd": 0.00001906,
      "usd_24h_change": -15.42412,
      "usd_market_cap": 158073,
      "usd_24h_vol": 11147.65
    },
    "x4pay": {
      "usd": 0.00001991,
      "usd_24h_change": -6.94394,
      "usd_market_cap": 19900.38,
      "usd_24h_vol": 363.76
    },
    "x402jobs": {
      "usd": 0.00001176,
      "usd_24h_change": 0.79386,
      "usd_market_cap": 11759.05,
      "usd_24h_vol": 22.86
    },
    "agentbank-x402-protocol": {
      "usd": 0.00000466,
      "usd_24h_change": null,
      "usd_market_cap": 4644.06,
      "usd_24h_vol": 29.26
    },
    "sol402-proxy": {
      "usd": 0.000003,
      "usd_24h_change": -0.00966,
      "usd_market_cap": 2998.66,
      "usd_24h_vol": 13.06
    },
    "bridge402": {
      "usd": 0.00000318,
      "usd_24h_change": null,
      "usd_market_cap": 2986.94,
      "usd_24h_vol": 1.75
    }
  },
  "sparklines": {
    "bitcoin": [
      [
        1776204464550,
        74100.7452778941
      ],
      [
        1776233264550,
        74341.62437331716
      ],
      [
        1776262064550,
        74032.58109612072
      ],
      [
        1776290864550,
        74381.43657451161
      ],
      [
        1776319664550,
        74960.58296925222
      ],
      [
        1776348464550,
        74332.7583953483
      ],
      [
        1776377264550,
        75017.42674367223
      ],
      [
        1776406064550,
        74695.48255658832
      ],
      [
        1776434864550,
        75297.00919396247
      ],
      [
        1776463664550,
        77164.03670386429
      ],
      [
        1776492464550,
        77315.4096324451
      ],
      [
        1776521264550,
        76188.45755869409
      ],
      [
        1776550064550,
        75653.54136303878
      ],
      [
        1776578864550,
        75558.77945979389
      ],
      [
        1776607664550,
        75236.36654292562
      ],
      [
        1776636464550,
        74795.1465182244
      ],
      [
        1776665264550,
        74458.21813860718
      ],
      [
        1776694064550,
        75045.02524645194
      ],
      [
        1776722864550,
        76437.62877231697
      ],
      [
        1776751664550,
        75628.03723799669
      ],
      [
        1776780464550,
        76784.39417696862
      ]
    ],
    "eigenlayer": [
      [
        1776204464550,
        0.15852727101475067
      ],
      [
        1776233264550,
        0.16072945484557868
      ],
      [
        1776262064550,
        0.16300407882003964
      ],
      [
        1776290864550,
        0.16958873174868744
      ],
      [
        1776319664550,
        0.1740096381459367
      ],
      [
        1776348464550,
        0.18190059621137936
      ],
      [
        1776377264550,
        0.20192582774950485
      ],
      [
        1776406064550,
        0.1973888897581448
      ],
      [
        1776434864550,
        0.19522113610491312
      ],
      [
        1776463664550,
        0.20738197329661615
      ],
      [
        1776492464550,
        0.19736488470634697
      ],
      [
        1776521264550,
        0.18643571910566875
      ],
      [
        1776550064550,
        0.18251917810430432
      ],
      [
        1776578864550,
        0.17636488390675306
      ],
      [
        1776607664550,
        0.17362541229671302
      ],
      [
        1776636464550,
        0.16984233184586367
      ],
      [
        1776665264550,
        0.17845319958332406
      ],
      [
        1776694064550,
        0.18490401331435827
      ],
      [
        1776722864550,
        0.18371703412496204
      ],
      [
        1776751664550,
        0.17915408768411983
      ],
      [
        1776780464550,
        0.18083867380423446
      ]
    ],
    "unibase": [
      [
        1776204464550,
        0.023336977663256212
      ],
      [
        1776233264550,
        0.02440546817612287
      ],
      [
        1776262064550,
        0.023910061283207412
      ],
      [
        1776290864550,
        0.026461892548326656
      ],
      [
        1776319664550,
        0.029722636808867386
      ],
      [
        1776348464550,
        0.03184117787318328
      ],
      [
        1776377264550,
        0.03358004552362194
      ],
      [
        1776406064550,
        0.03353561887423254
      ],
      [
        1776434864550,
        0.03819099098864783
      ],
      [
        1776463664550,
        0.03945747352304124
      ],
      [
        1776492464550,
        0.039679994239733535
      ],
      [
        1776521264550,
        0.039800328521467566
      ],
      [
        1776550064550,
        0.040923786549483185
      ],
      [
        1776578864550,
        0.04346223744742007
      ],
      [
        1776607664550,
        0.04294099747508645
      ],
      [
        1776636464550,
        0.04197539617967814
      ],
      [
        1776665264550,
        0.04090987926906162
      ],
      [
        1776694064550,
        0.04317692385530932
      ],
      [
        1776722864550,
        0.04224993391776869
      ],
      [
        1776751664550,
        0.04006887352346523
      ],
      [
        1776780464550,
        0.0417439624261631
      ]
    ],
    "concordium": [
      [
        1776204464550,
        0.004624754953673855
      ],
      [
        1776233264550,
        0.004837372799029968
      ],
      [
        1776262064550,
        0.005016715406843566
      ],
      [
        1776290864550,
        0.005108231412909971
      ],
      [
        1776319664550,
        0.004955733430015155
      ],
      [
        1776348464550,
        0.004868162375789707
      ],
      [
        1776377264550,
        0.004788857152627505
      ],
      [
        1776406064550,
        0.004838064750357706
      ],
      [
        1776434864550,
        0.004742856945655095
      ],
      [
        1776463664550,
        0.00480530091848969
      ],
      [
        1776492464550,
        0.005000190174776682
      ],
      [
        1776521264550,
        0.004970186760636066
      ],
      [
        1776550064550,
        0.004835838007786826
      ],
      [
        1776578864550,
        0.004800202301802834
      ],
      [
        1776607664550,
        0.004766714200959067
      ],
      [
        1776636464550,
        0.004773903850434123
      ],
      [
        1776665264550,
        0.00488985419780484
      ],
      [
        1776694064550,
        0.0048613583659373565
      ],
      [
        1776722864550,
        0.004904747154609949
      ],
      [
        1776751664550,
        0.00483290199579438
      ],
      [
        1776780464550,
        0.004725096573797839
      ]
    ],
    "skale": [
      [
        1776204464551,
        0.006271057087993788
      ],
      [
        1776233264551,
        0.006239909670265686
      ],
      [
        1776262064551,
        0.0062339282413537665
      ],
      [
        1776290864551,
        0.006419124690340757
      ],
      [
        1776319664551,
        0.0064242354663518455
      ],
      [
        1776348464551,
        0.006419934918014764
      ],
      [
        1776377264551,
        0.006688654358603821
      ],
      [
        1776406064551,
        0.006736696903092053
      ],
      [
        1776434864551,
        0.006771459092194167
      ],
      [
        1776463664551,
        0.00797766871443982
      ],
      [
        1776492464551,
        0.007733114280071486
      ],
      [
        1776521264551,
        0.007347913846656108
      ],
      [
        1776550064551,
        0.007018420758859012
      ],
      [
        1776578864551,
        0.006817658817844841
      ],
      [
        1776607664551,
        0.006994365266705553
      ],
      [
        1776636464551,
        0.006835149467968382
      ],
      [
        1776665264551,
        0.00682386199813122
      ],
      [
        1776694064551,
        0.006950709965271494
      ],
      [
        1776722864551,
        0.00715711539978574
      ],
      [
        1776751664551,
        0.007115584026419968
      ],
      [
        1776780464551,
        0.00714773122997223
      ]
    ],
    "peaq-2": [
      [
        1776204464551,
        0.013692137431122247
      ],
      [
        1776233264551,
        0.01380310963888629
      ],
      [
        1776262064551,
        0.014313019835590064
      ],
      [
        1776290864551,
        0.014669248788825546
      ],
      [
        1776319664551,
        0.014342174786706475
      ],
      [
        1776348464551,
        0.015362125346511426
      ],
      [
        1776377264551,
        0.015140605157335982
      ],
      [
        1776406064551,
        0.016486501375811133
      ],
      [
        1776434864551,
        0.017195196797206058
      ],
      [
        1776463664551,
        0.01759744896928195
      ],
      [
        1776492464551,
        0.017648681020271745
      ],
      [
        1776521264551,
        0.016916800398304597
      ],
      [
        1776550064551,
        0.01623409440970599
      ],
      [
        1776578864551,
        0.015371301013963425
      ],
      [
        1776607664551,
        0.016056043522228343
      ],
      [
        1776636464551,
        0.01584125629540415
      ],
      [
        1776665264551,
        0.015602283708016453
      ],
      [
        1776694064551,
        0.01518418802309379
      ],
      [
        1776722864551,
        0.017009160493157274
      ],
      [
        1776751664551,
        0.01649414006573324
      ],
      [
        1776780464551,
        0.01650439886817348
      ]
    ],
    "bankercoin-2": [
      [
        1776204464551,
        0.000379937821347851
      ],
      [
        1776233264551,
        0.0003683443960554787
      ],
      [
        1776262064551,
        0.00035501636031756814
      ],
      [
        1776290864551,
        0.00036300632136050014
      ],
      [
        1776319664551,
        0.0003620405739998629
      ],
      [
        1776348464551,
        0.0003585282175081488
      ],
      [
        1776377264551,
        0.00035344868487951803
      ],
      [
        1776406064551,
        0.00035425320423603657
      ],
      [
        1776434864551,
        0.0003574320297521588
      ],
      [
        1776463664551,
        0.00037173972729583445
      ],
      [
        1776492464551,
        0.0003684146546823108
      ],
      [
        1776521264551,
        0.00035983612012681083
      ],
      [
        1776550064551,
        0.00035166787457721756
      ],
      [
        1776578864551,
        0.00035708079221442705
      ],
      [
        1776607664551,
        0.0003629316868320672
      ],
      [
        1776636464551,
        0.00034928179733268583
      ],
      [
        1776665264551,
        0.0003237024655903488
      ],
      [
        1776694064551,
        0.00033033683275313335
      ],
      [
        1776722864551,
        0.0003413767181989612
      ],
      [
        1776751664551,
        0.0003387376925628364
      ],
      [
        1776780464551,
        0.00033794053198603753
      ]
    ],
    "amiko": [
      [
        1776204464551,
        0.03982068524721625
      ],
      [
        1776233264551,
        0.03934847715127021
      ],
      [
        1776262064551,
        0.04022565192260534
      ],
      [
        1776290864551,
        0.03958614363517664
      ],
      [
        1776319664551,
        0.03977038284715638
      ],
      [
        1776348464551,
        0.03981061926934349
      ],
      [
        1776377264551,
        0.03993572717823322
      ],
      [
        1776406064551,
        0.04008348100753858
      ],
      [
        1776434864551,
        0.03913040715436194
      ],
      [
        1776463664551,
        0.03958989962713386
      ],
      [
        1776492464551,
        0.04031331762828215
      ],
      [
        1776521264551,
        0.03892407123383319
      ],
      [
        1776550064551,
        0.03766085112379608
      ],
      [
        1776578864551,
        0.039092107432939296
      ],
      [
        1776607664551,
        0.038124299962995725
      ],
      [
        1776636464551,
        0.035047999520480246
      ],
      [
        1776665264551,
        0.03691886504438004
      ],
      [
        1776694064551,
        0.03698500794764185
      ],
      [
        1776722864551,
        0.03764279963722248
      ],
      [
        1776751664551,
        0.03618800090790332
      ],
      [
        1776780464551,
        0.035623913141209614
      ]
    ],
    "flock-2": [
      [
        1776204464551,
        0.055611378658495754
      ],
      [
        1776233264551,
        0.05611644532201609
      ],
      [
        1776262064551,
        0.05968973105449112
      ],
      [
        1776290864551,
        0.06110788847909875
      ],
      [
        1776319664551,
        0.06146714488503017
      ],
      [
        1776348464551,
        0.05963029506092843
      ],
      [
        1776377264551,
        0.060229651579451204
      ],
      [
        1776406064551,
        0.05924853830894134
      ],
      [
        1776434864551,
        0.059053078285582594
      ],
      [
        1776463664551,
        0.06070903620005809
      ],
      [
        1776492464551,
        0.06295027273156337
      ],
      [
        1776521264551,
        0.060281794229105
      ],
      [
        1776550064551,
        0.06087017303598928
      ],
      [
        1776578864551,
        0.05827746802064234
      ],
      [
        1776607664551,
        0.05899732914938379
      ],
      [
        1776636464551,
        0.057591056020846076
      ],
      [
        1776665264551,
        0.057536498271974115
      ],
      [
        1776694064551,
        0.059652652707137335
      ],
      [
        1776722864551,
        0.05946300944828454
      ],
      [
        1776751664551,
        0.06272148083620359
      ],
      [
        1776780464551,
        0.06353568892652947
      ]
    ],
    "magic": [
      [
        1776204464551,
        0.06020904125937367
      ],
      [
        1776233264551,
        0.06153737300500016
      ],
      [
        1776262064551,
        0.06165078353321773
      ],
      [
        1776290864551,
        0.06399795328624158
      ],
      [
        1776319664551,
        0.06489636611789883
      ],
      [
        1776348464551,
        0.06519376977220132
      ],
      [
        1776377264551,
        0.06662814617623466
      ],
      [
        1776406064551,
        0.0671791188487217
      ],
      [
        1776434864551,
        0.06746952723744751
      ],
      [
        1776463664551,
        0.0681534889202367
      ],
      [
        1776492464551,
        0.07009357593828879
      ],
      [
        1776521264551,
        0.06972507738414077
      ],
      [
        1776550064551,
        0.06510599884892594
      ],
      [
        1776578864551,
        0.06382764566376581
      ],
      [
        1776607664551,
        0.06362805918703837
      ],
      [
        1776636464551,
        0.06311859904753528
      ],
      [
        1776665264551,
        0.06321935520139617
      ],
      [
        1776694064551,
        0.0636525220595619
      ],
      [
        1776722864551,
        0.0656409954399097
      ],
      [
        1776751664551,
        0.06519327735328179
      ],
      [
        1776780464551,
        0.06457310855249748
      ]
    ],
    "elsa": [
      [
        1776204464551,
        0.06723871657529959
      ],
      [
        1776233264551,
        0.0676374890676512
      ],
      [
        1776262064551,
        0.06963234636235069
      ],
      [
        1776290864551,
        0.07161127732037965
      ],
      [
        1776319664551,
        0.07106720716830685
      ],
      [
        1776348464551,
        0.07034855057714111
      ],
      [
        1776377264551,
        0.07096974272377511
      ],
      [
        1776406064551,
        0.07240116273443903
      ],
      [
        1776434864551,
        0.07091969155375351
      ],
      [
        1776463664551,
        0.0761345893167971
      ],
      [
        1776492464551,
        0.0735731647819177
      ],
      [
        1776521264551,
        0.07283050112006806
      ],
      [
        1776550064551,
        0.07335271716545054
      ],
      [
        1776578864551,
        0.06870861121254658
      ],
      [
        1776607664551,
        0.06868753544199396
      ],
      [
        1776636464551,
        0.06720055425312076
      ],
      [
        1776665264551,
        0.06809613102500778
      ],
      [
        1776694064551,
        0.06866741241376954
      ],
      [
        1776722864551,
        0.06851414796215025
      ],
      [
        1776751664551,
        0.06803365124637373
      ],
      [
        1776780464551,
        0.06839909145921765
      ]
    ],
    "openserv": [
      [
        1776204464551,
        0.023838039792925047
      ],
      [
        1776233264551,
        0.022853666243516854
      ],
      [
        1776262064551,
        0.0234731014226808
      ],
      [
        1776290864551,
        0.023463364950782675
      ],
      [
        1776319664551,
        0.023353941143259428
      ],
      [
        1776348464551,
        0.023642278992151607
      ],
      [
        1776377264551,
        0.024276821753650913
      ],
      [
        1776406064551,
        0.024908411374161908
      ],
      [
        1776434864551,
        0.026385277320503858
      ],
      [
        1776463664551,
        0.028054592246936627
      ],
      [
        1776492464551,
        0.027058970484059804
      ],
      [
        1776521264551,
        0.02587350139591905
      ],
      [
        1776550064551,
        0.024331431692391343
      ],
      [
        1776578864551,
        0.023395608601357976
      ],
      [
        1776607664551,
        0.021055846695129152
      ],
      [
        1776636464551,
        0.02054037418839161
      ],
      [
        1776665264551,
        0.02096451006315574
      ],
      [
        1776694064551,
        0.019708953365546476
      ],
      [
        1776722864551,
        0.01926979546708346
      ],
      [
        1776751664551,
        0.01954175482536142
      ],
      [
        1776780464551,
        0.01897153746354922
      ]
    ],
    "autonolas": [
      [
        1776204464551,
        0.043976875429412726
      ],
      [
        1776233264551,
        0.04407330353523235
      ],
      [
        1776262064551,
        0.04323984466684306
      ],
      [
        1776290864551,
        0.04360061945311067
      ],
      [
        1776319664551,
        0.04366841925942634
      ],
      [
        1776348464551,
        0.04382442848727801
      ],
      [
        1776377264551,
        0.04363139275569417
      ],
      [
        1776406064551,
        0.04394210347382626
      ],
      [
        1776434864551,
        0.04407608717989588
      ],
      [
        1776463664551,
        0.04476791197076072
      ],
      [
        1776492464551,
        0.044825618002675
      ],
      [
        1776521264551,
        0.04411859597290363
      ],
      [
        1776550064551,
        0.04389787596819349
      ],
      [
        1776578864551,
        0.04296131245307459
      ],
      [
        1776607664551,
        0.04276277098882233
      ],
      [
        1776636464551,
        0.04281320668374776
      ],
      [
        1776665264551,
        0.04229455564242143
      ],
      [
        1776694064551,
        0.042098534959456646
      ],
      [
        1776722864551,
        0.04183417636375405
      ],
      [
        1776751664551,
        0.04144399366186719
      ],
      [
        1776780464551,
        0.04117255724787056
      ]
    ],
    "anyspend": [
      [
        1776204464551,
        0.03379718569738023
      ],
      [
        1776234516724.913,
        0.03391724659185117
      ],
      [
        1776264568898.8262,
        0.03392148287010133
      ],
      [
        1776294621072.739,
        0.03419536633211817
      ],
      [
        1776324673246.652,
        0.0343814838312871
      ],
      [
        1776354725420.5652,
        0.034141684232387004
      ],
      [
        1776384777594.4783,
        0.034292562927078614
      ],
      [
        1776414829768.3914,
        0.03398903168208852
      ],
      [
        1776444881942.3044,
        0.03570197275143008
      ],
      [
        1776474934116.2173,
        0.03319170785501445
      ],
      [
        1776504986290.1304,
        0.03261235923032281
      ],
      [
        1776535038464.0435,
        0.032380014780062104
      ],
      [
        1776565090637.9565,
        0.03506559109336847
      ],
      [
        1776595142811.8696,
        0.03449813958245661
      ],
      [
        1776625194985.7827,
        0.03440957151818075
      ],
      [
        1776655247159.6956,
        0.033909520940875834
      ],
      [
        1776685299333.6086,
        0.03440206467919953
      ],
      [
        1776715351507.5217,
        0.034512418462353034
      ],
      [
        1776745403681.4348,
        0.03443166803479616
      ],
      [
        1776775455855.348,
        0.0346309561204104
      ],
      [
        1776805508029.261,
        0.034315157822842716
      ]
    ],
    "zauthx402": [
      [
        1776204464551,
        0.00477165740436403
      ],
      [
        1776233611538.952,
        0.004442967388677834
      ],
      [
        1776262758526.9036,
        0.004478455177873595
      ],
      [
        1776291905514.8555,
        0.004397688196538511
      ],
      [
        1776321052502.8071,
        0.004890554363429248
      ],
      [
        1776350199490.759,
        0.004995622113512214
      ],
      [
        1776379346478.711,
        0.0049163279191770165
      ],
      [
        1776408493466.6626,
        0.0046029513139322605
      ],
      [
        1776437640454.6145,
        0.004494776482580382
      ],
      [
        1776466787442.5662,
        0.004335981148902931
      ],
      [
        1776495934430.518,
        0.004234328537077623
      ],
      [
        1776525081418.47,
        0.004214974098166586
      ],
      [
        1776554228406.4216,
        0.00392629289028022
      ],
      [
        1776583375394.3735,
        0.0038055805224788374
      ],
      [
        1776612522382.3252,
        0.0036218652708176315
      ],
      [
        1776641669370.277,
        0.0040259041313855755
      ],
      [
        1776670816358.229,
        0.0041891878062343185
      ],
      [
        1776699963346.1807,
        0.0038016444308748435
      ],
      [
        1776729110334.1326,
        0.003912263244822441
      ],
      [
        1776758257322.0842,
        0.003705898981517444
      ],
      [
        1776787404310.0361,
        0.0037729189709161037
      ]
    ],
    "daydreams": [
      [
        1776204464551,
        0.005750896900194096
      ],
      [
        1776233611538.952,
        0.005576117114603201
      ],
      [
        1776262758526.9036,
        0.0051710329297667045
      ],
      [
        1776291905514.8555,
        0.004754028015454137
      ],
      [
        1776321052502.8071,
        0.004799738930553748
      ],
      [
        1776350199490.759,
        0.004644095099629314
      ],
      [
        1776379346478.711,
        0.004512804656007735
      ],
      [
        1776408493466.6626,
        0.004649004315729004
      ],
      [
        1776437640454.6145,
        0.004515158724269959
      ],
      [
        1776466787442.5662,
        0.004836093046942584
      ],
      [
        1776495934430.518,
        0.004762630943293655
      ],
      [
        1776525081418.47,
        0.00465915079929203
      ],
      [
        1776554228406.4216,
        0.004612824408103816
      ],
      [
        1776583375394.3735,
        0.004419318724667775
      ],
      [
        1776612522382.3252,
        0.004491744004812374
      ],
      [
        1776641669370.277,
        0.004429807707723907
      ],
      [
        1776670816358.229,
        0.004444383474780676
      ],
      [
        1776699963346.1807,
        0.004430274125797909
      ],
      [
        1776729110334.1326,
        0.004507124863790541
      ],
      [
        1776758257322.0842,
        0.004435003124778715
      ],
      [
        1776787404310.0361,
        0.004486917346688328
      ]
    ],
    "payai-network-2": [
      [
        1776204464552,
        0.0025937708788345065
      ],
      [
        1776233611539.952,
        0.0025652403515196444
      ],
      [
        1776262758527.9036,
        0.0026043161089688792
      ],
      [
        1776291905515.8555,
        0.002838110745024247
      ],
      [
        1776321052503.8071,
        0.00274018714894616
      ],
      [
        1776350199491.759,
        0.002954222839323858
      ],
      [
        1776379346479.711,
        0.0031549644019629886
      ],
      [
        1776408493467.6626,
        0.0030409500158156857
      ],
      [
        1776437640455.6145,
        0.0029223567058179944
      ],
      [
        1776466787443.5662,
        0.0032618059454301357
      ],
      [
        1776495934431.518,
        0.003100831745736091
      ],
      [
        1776525081419.47,
        0.0029211109388852553
      ],
      [
        1776554228407.4216,
        0.0029228322282536024
      ],
      [
        1776583375395.3735,
        0.002818259167962369
      ],
      [
        1776612522383.3252,
        0.0027769949390728695
      ],
      [
        1776641669371.277,
        0.0026191646392778323
      ],
      [
        1776670816359.229,
        0.002653743586427438
      ],
      [
        1776699963347.1807,
        0.0027761441659588716
      ],
      [
        1776729110335.1326,
        0.00290784440030578
      ],
      [
        1776758257323.0842,
        0.002909996638619554
      ],
      [
        1776787404311.0361,
        0.003060933103659462
      ]
    ],
    "coral-protocol": [
      [
        1776204464552,
        0.0002726671769191271
      ],
      [
        1776233611539.952,
        0.00027133042724030836
      ],
      [
        1776262758527.9036,
        0.0002716927531809741
      ],
      [
        1776291905515.8555,
        0.00027278576254196235
      ],
      [
        1776321052503.8071,
        0.00025825501994102446
      ],
      [
        1776350199491.759,
        0.00025821942511248543
      ],
      [
        1776379346479.711,
        0.00027025004580170356
      ],
      [
        1776408493467.6626,
        0.0002645479679126098
      ],
      [
        1776437640455.6145,
        0.0002690306997273696
      ],
      [
        1776466787443.5662,
        0.00026993396971359483
      ],
      [
        1776495934431.518,
        0.0002686529407925893
      ],
      [
        1776525081419.47,
        0.00026334104381716696
      ],
      [
        1776554228407.4216,
        0.0002573620787047971
      ],
      [
        1776583375395.3735,
        0.0002547558770828414
      ],
      [
        1776612522383.3252,
        0.0002554439471453987
      ],
      [
        1776641669371.277,
        0.00023761989105762062
      ],
      [
        1776670816359.229,
        0.000239756224198205
      ],
      [
        1776699963347.1807,
        0.00024183867394499532
      ],
      [
        1776729110335.1326,
        0.00024274037022670958
      ],
      [
        1776758257323.0842,
        0.00024061421430627948
      ],
      [
        1776787404311.0361,
        0.00024048379818562122
      ]
    ],
    "cod3x": [
      [
        1776204464552,
        0.041891085389847725
      ],
      [
        1776233611539.952,
        0.04134290421111762
      ],
      [
        1776262758527.9036,
        0.041386608251735534
      ],
      [
        1776291905515.8555,
        0.042618812266099565
      ],
      [
        1776321052503.8071,
        0.042504460578887335
      ],
      [
        1776350199491.759,
        0.04328225949117792
      ],
      [
        1776379346479.711,
        0.039843107237877214
      ],
      [
        1776408493467.6626,
        0.039399874236503485
      ],
      [
        1776437640455.6145,
        0.03937857990294176
      ],
      [
        1776466787443.5662,
        0.04058151010967814
      ],
      [
        1776495934431.518,
        0.04019787192968548
      ],
      [
        1776525081419.47,
        0.039299913058018415
      ],
      [
        1776554228407.4216,
        0.03929029159785996
      ],
      [
        1776583375395.3735,
        0.03884344822111407
      ],
      [
        1776612522383.3252,
        0.038761653302487424
      ],
      [
        1776641669371.277,
        0.0382388602731306
      ],
      [
        1776670816359.229,
        0.040211329311059245
      ],
      [
        1776699963347.1807,
        0.04044885937692303
      ],
      [
        1776729110335.1326,
        0.04157838972435305
      ],
      [
        1776758257323.0842,
        0.041006880786381095
      ],
      [
        1776787404311.0361,
        0.041102559404796415
      ]
    ],
    "ping": [
      [
        1776204464552,
        0.0017658416015188308
      ],
      [
        1776233611539.952,
        0.0017354048660969458
      ],
      [
        1776262758527.9036,
        0.001763116155644726
      ],
      [
        1776291905515.8555,
        0.0017941214286841226
      ],
      [
        1776321052503.8071,
        0.002002109702954457
      ],
      [
        1776350199491.759,
        0.0022510620407296227
      ],
      [
        1776379346479.711,
        0.0021948998805585342
      ],
      [
        1776408493467.6626,
        0.0023923518346780446
      ],
      [
        1776437640455.6145,
        0.0020960374539828425
      ],
      [
        1776466787443.5662,
        0.0020752505282286473
      ],
      [
        1776495934431.518,
        0.002017401462732217
      ],
      [
        1776525081419.47,
        0.001982598911992622
      ],
      [
        1776554228407.4216,
        0.0019421534626724393
      ],
      [
        1776583375395.3735,
        0.0018958279741815678
      ],
      [
        1776612522383.3252,
        0.0018158371676728585
      ],
      [
        1776641669371.277,
        0.0017997345356316977
      ],
      [
        1776670816359.229,
        0.001744820956232161
      ],
      [
        1776699963347.1807,
        0.0016939785782934718
      ],
      [
        1776729110335.1326,
        0.0015996314649439163
      ],
      [
        1776758257323.0842,
        0.001514038620248453
      ],
      [
        1776787404311.0361,
        0.0017260751328609368
      ]
    ],
    "aubrai-by-bio": [
      [
        1776204464552,
        0.7557562172712882
      ],
      [
        1776233611539.952,
        0.75186685074692
      ],
      [
        1776262758527.9036,
        0.9596103537898341
      ],
      [
        1776291905515.8555,
        1.0394778214205047
      ],
      [
        1776321052503.8071,
        1.670784249173723
      ],
      [
        1776350199491.759,
        1.4484369241516157
      ],
      [
        1776379346479.711,
        1.3841441134462342
      ],
      [
        1776408493467.6626,
        1.3346542145875047
      ],
      [
        1776437640455.6145,
        1.212754369773286
      ],
      [
        1776466787443.5662,
        1.1540160423227304
      ],
      [
        1776495934431.518,
        1.126083863438919
      ],
      [
        1776525081419.47,
        1.0379733449381294
      ],
      [
        1776554228407.4216,
        1.0934113179546274
      ],
      [
        1776583375395.3735,
        1.1462500673863552
      ],
      [
        1776612522383.3252,
        1.1570164251341386
      ],
      [
        1776641669371.277,
        1.0680576838478157
      ],
      [
        1776670816359.229,
        1.0580687464683611
      ],
      [
        1776699963347.1807,
        1.0319509462365497
      ],
      [
        1776729110335.1326,
        1.0652284491876376
      ],
      [
        1776758257323.0842,
        1.0784213479642866
      ],
      [
        1776787404311.0361,
        1.1033235760613351
      ]
    ],
    "alphakek-ai": [
      [
        1776204464552,
        0.004303674339340374
      ],
      [
        1776233611539.952,
        0.004312814598487904
      ],
      [
        1776262758527.9036,
        0.004267708124136431
      ],
      [
        1776291905515.8555,
        0.00433034436564058
      ],
      [
        1776321052503.8071,
        0.004351369188189486
      ],
      [
        1776350199491.759,
        0.004255456092355585
      ],
      [
        1776379346479.711,
        0.004389940210293394
      ],
      [
        1776408493467.6626,
        0.004295099665866066
      ],
      [
        1776437640455.6145,
        0.004409478077692074
      ],
      [
        1776466787443.5662,
        0.004820759026010557
      ],
      [
        1776495934431.518,
        0.004718754960663733
      ],
      [
        1776525081419.47,
        0.004733011680210673
      ],
      [
        1776554228407.4216,
        0.00467711012107453
      ],
      [
        1776583375395.3735,
        0.0046491321638977
      ],
      [
        1776612522383.3252,
        0.004706796351236009
      ],
      [
        1776641669371.277,
        0.004540648870901758
      ],
      [
        1776670816359.229,
        0.004440591741027639
      ],
      [
        1776699963347.1807,
        0.00442233322207063
      ],
      [
        1776729110335.1326,
        0.004531576998084399
      ],
      [
        1776758257323.0842,
        0.004463042615241749
      ],
      [
        1776787404311.0361,
        0.004463933472059614
      ]
    ],
    "homebrew-robotics-club": [
      [
        1776204464552,
        0.0008744858970607029
      ],
      [
        1776233611539.952,
        0.0009396361016844094
      ],
      [
        1776262758527.9036,
        0.001460724243664934
      ],
      [
        1776291905515.8555,
        0.0012994894559460225
      ],
      [
        1776321052503.8071,
        0.001208344840542461
      ],
      [
        1776350199491.759,
        0.00115870286805423
      ],
      [
        1776379346479.711,
        0.001253489204817966
      ],
      [
        1776408493467.6626,
        0.0011202589919654332
      ],
      [
        1776437640455.6145,
        0.0012594666188990558
      ],
      [
        1776466787443.5662,
        0.001349539988466614
      ],
      [
        1776495934431.518,
        0.0012521447698077839
      ],
      [
        1776525081419.47,
        0.0011667410819789802
      ],
      [
        1776554228407.4216,
        0.0009685519877458081
      ],
      [
        1776583375395.3735,
        0.0009796126508076824
      ],
      [
        1776612522383.3252,
        0.0011123961178022802
      ],
      [
        1776641669371.277,
        0.0011361620011215961
      ],
      [
        1776670816359.229,
        0.0013420364698428818
      ],
      [
        1776699963347.1807,
        0.001311681938189687
      ],
      [
        1776729110335.1326,
        0.0011821269407061039
      ],
      [
        1776758257323.0842,
        0.0012391258417994836
      ],
      [
        1776787404311.0361,
        0.0011855509375741328
      ]
    ],
    "ethy-ai": [
      [
        1776204464552,
        0.0011185788508384518
      ],
      [
        1776233611539.952,
        0.0011103897014317404
      ],
      [
        1776262758527.9036,
        0.0011206843068171306
      ],
      [
        1776291905515.8555,
        0.0011178662870098253
      ],
      [
        1776321052503.8071,
        0.0011240575476400034
      ],
      [
        1776350199491.759,
        0.0012129288610544203
      ],
      [
        1776379346479.711,
        0.0012812353671638275
      ],
      [
        1776408493467.6626,
        0.0011912327151516768
      ],
      [
        1776437640455.6145,
        0.0012604740986339221
      ],
      [
        1776466787443.5662,
        0.0012684342435895812
      ],
      [
        1776495934431.518,
        0.0013491649181547936
      ],
      [
        1776525081419.47,
        0.0012073947988781263
      ],
      [
        1776554228407.4216,
        0.0012055188731532251
      ],
      [
        1776583375395.3735,
        0.0011567371269407326
      ],
      [
        1776612522383.3252,
        0.001204165095225869
      ],
      [
        1776641669371.277,
        0.0011513038148631776
      ],
      [
        1776670816359.229,
        0.0011325961819550446
      ],
      [
        1776699963347.1807,
        0.0011338114570354921
      ],
      [
        1776729110335.1326,
        0.0011625469006258584
      ],
      [
        1776758257323.0842,
        0.0011290893708977697
      ],
      [
        1776787404311.0361,
        0.0010122001665588477
      ]
    ],
    "santa-by-virtuals": [
      [
        1776204464552,
        0.0010056021305929214
      ],
      [
        1776233611539.952,
        0.0010140413723807055
      ],
      [
        1776262758527.9036,
        0.001019280215007461
      ],
      [
        1776291905515.8555,
        0.0010411725042568205
      ],
      [
        1776321052503.8071,
        0.0010805144784079934
      ],
      [
        1776350199491.759,
        0.0011331579696597178
      ],
      [
        1776379346479.711,
        0.0011917500437671328
      ],
      [
        1776408493467.6626,
        0.0011362163839225218
      ],
      [
        1776437640455.6145,
        0.0011897090175622532
      ],
      [
        1776466787443.5662,
        0.0012895711077062187
      ],
      [
        1776495934431.518,
        0.001258018057722672
      ],
      [
        1776525081419.47,
        0.001179285294023884
      ],
      [
        1776554228407.4216,
        0.0011674958455320922
      ],
      [
        1776583375395.3735,
        0.001065140148675149
      ],
      [
        1776612522383.3252,
        0.001087609704527444
      ],
      [
        1776641669371.277,
        0.0010478220582791722
      ],
      [
        1776670816359.229,
        0.0010372011324012891
      ],
      [
        1776699963347.1807,
        0.0010407271302119634
      ],
      [
        1776729110335.1326,
        0.0009449610956412144
      ],
      [
        1776758257323.0842,
        0.0008574802237439698
      ],
      [
        1776787404311.0361,
        0.0009737236115929959
      ]
    ],
    "heurist": [
      [
        1776204464552,
        0.00530352055661034
      ],
      [
        1776233611539.952,
        0.0051214535241968446
      ],
      [
        1776262758527.9036,
        0.005040021859237437
      ],
      [
        1776291905515.8555,
        0.005001000435637546
      ],
      [
        1776321052503.8071,
        0.004980852196856755
      ],
      [
        1776350199491.759,
        0.004990254729798906
      ],
      [
        1776379346479.711,
        0.0048893597294335026
      ],
      [
        1776408493467.6626,
        0.004683996856913972
      ],
      [
        1776437640455.6145,
        0.004680777869265939
      ],
      [
        1776466787443.5662,
        0.00466280070004802
      ],
      [
        1776495934431.518,
        0.004696549536536586
      ],
      [
        1776525081419.47,
        0.004703769991644147
      ],
      [
        1776554228407.4216,
        0.004691401491567653
      ],
      [
        1776583375395.3735,
        0.004691339900475257
      ],
      [
        1776612522383.3252,
        0.0046990921691891134
      ],
      [
        1776641669371.277,
        0.004685891885754239
      ],
      [
        1776670816359.229,
        0.004590167824404403
      ],
      [
        1776699963347.1807,
        0.00444377598105298
      ],
      [
        1776729110335.1326,
        0.0045828140902645555
      ],
      [
        1776758257323.0842,
        0.004553365664566878
      ],
      [
        1776787404311.0361,
        0.0045245598704682245
      ]
    ],
    "dexter-ai": [
      [
        1776204464552,
        0.0008807362362623964
      ],
      [
        1776233611539.952,
        0.0008231866892966313
      ],
      [
        1776262758527.9036,
        0.0008873107923391112
      ],
      [
        1776291905515.8555,
        0.0008893934098974662
      ],
      [
        1776321052503.8071,
        0.0011185143300841268
      ],
      [
        1776350199491.759,
        0.0011193722656370202
      ],
      [
        1776379346479.711,
        0.0011280085862728857
      ],
      [
        1776408493467.6626,
        0.001199532494729139
      ],
      [
        1776437640455.6145,
        0.001175696717139568
      ],
      [
        1776466787443.5662,
        0.001235062903498256
      ],
      [
        1776495934431.518,
        0.0010141407450412901
      ],
      [
        1776525081419.47,
        0.0009908475398361883
      ],
      [
        1776554228407.4216,
        0.0010496717017056724
      ],
      [
        1776583375395.3735,
        0.0010071539628291205
      ],
      [
        1776612522383.3252,
        0.0009168860485129094
      ],
      [
        1776641669371.277,
        0.0008674985107342241
      ],
      [
        1776670816359.229,
        0.0009702716084266218
      ],
      [
        1776699963347.1807,
        0.0009674679757105919
      ],
      [
        1776729110335.1326,
        0.001032950179078152
      ],
      [
        1776758257323.0842,
        0.000925696490725923
      ],
      [
        1776787404311.0361,
        0.0008966664829600885
      ]
    ],
    "0xgasless-2": [
      [
        1776204464553,
        0.04678731839859191
      ],
      [
        1776233069958.4055,
        0.0428334916486341
      ],
      [
        1776261675363.8108,
        0.043580729462027304
      ],
      [
        1776290280769.2163,
        0.043005443303948274
      ],
      [
        1776318886174.6216,
        0.045706066127886545
      ],
      [
        1776347491580.027,
        0.04482859650527142
      ],
      [
        1776376096985.4324,
        0.04376359823326989
      ],
      [
        1776404702390.838,
        0.04418238897409365
      ],
      [
        1776433307796.2432,
        0.058107201276809586
      ],
      [
        1776461913201.6487,
        0.05885425734288084
      ],
      [
        1776490518607.054,
        0.06018197305503066
      ],
      [
        1776519124012.4595,
        0.06234858620277369
      ],
      [
        1776547729417.8647,
        0.06351277396490194
      ],
      [
        1776576334823.2703,
        0.05781347495617531
      ],
      [
        1776604940228.6758,
        0.057752016073391414
      ],
      [
        1776633545634.081,
        0.05758512593875377
      ],
      [
        1776662151039.4866,
        0.056897896457700235
      ],
      [
        1776690756444.8918,
        0.057686105184086366
      ],
      [
        1776719361850.2974,
        0.0574975977096737
      ],
      [
        1776747967255.7026,
        0.058118997398195545
      ],
      [
        1776776572661.1082,
        0.05823101548369238
      ],
      [
        1776805178066.5134,
        0.057922808638383505
      ]
    ],
    "switchboard": [
      [
        1776204464553,
        0.0034282687373395656
      ],
      [
        1776233611540.952,
        0.003338445020464131
      ],
      [
        1776262758528.9036,
        0.003410365457408907
      ],
      [
        1776291905516.8555,
        0.003335251168482526
      ],
      [
        1776321052504.8071,
        0.0034353131008837585
      ],
      [
        1776350199492.759,
        0.0034102853554030194
      ],
      [
        1776379346480.711,
        0.0034145732364998264
      ],
      [
        1776408493468.6626,
        0.003440156644764013
      ],
      [
        1776437640456.6145,
        0.0033720326365629496
      ],
      [
        1776466787444.5662,
        0.003505930986228488
      ],
      [
        1776495934432.518,
        0.0034626739890362855
      ],
      [
        1776525081420.47,
        0.0033952711559656914
      ],
      [
        1776554228408.4216,
        0.0033311036092321454
      ],
      [
        1776583375396.3735,
        0.0033061818947389475
      ],
      [
        1776612522384.3252,
        0.0030973476514814355
      ],
      [
        1776641669372.277,
        0.0031018198782288833
      ],
      [
        1776670816360.229,
        0.0030414002821091
      ],
      [
        1776699963348.1807,
        0.0029566182775114893
      ],
      [
        1776729110336.1326,
        0.0029420369687799654
      ],
      [
        1776758257324.0842,
        0.0030083258171843203
      ],
      [
        1776787404312.0361,
        0.00310924723262447
      ]
    ],
    "sally-a1c": [
      [
        1776204464553,
        0.024169730322175773
      ],
      [
        1776231778101.3872,
        0.02389316551761127
      ],
      [
        1776259091649.7742,
        0.024232031360000246
      ],
      [
        1776286405198.1614,
        0.02420038808171699
      ],
      [
        1776313718746.5483,
        0.024156456639803633
      ],
      [
        1776341032294.9355,
        0.023762784937261958
      ],
      [
        1776368345843.3225,
        0.024087702851524742
      ],
      [
        1776395659391.7097,
        0.024001532367809563
      ],
      [
        1776422972940.0967,
        0.02414818055941531
      ],
      [
        1776450286488.484,
        0.024929549919545473
      ],
      [
        1776477600036.8708,
        0.024959463675568557
      ],
      [
        1776504913585.258,
        0.024546032818197703
      ],
      [
        1776532227133.6453,
        0.024269596834901687
      ],
      [
        1776559540682.0322,
        0.02436325183789996
      ],
      [
        1776586854230.4194,
        0.024137494662888045
      ],
      [
        1776614167778.8064,
        0.0239121619410457
      ],
      [
        1776641481327.1936,
        0.023729518839509908
      ],
      [
        1776668794875.5806,
        0.023536653204528725
      ],
      [
        1776696108423.9678,
        0.023847461388655233
      ],
      [
        1776723421972.3547,
        0.023660134567656796
      ],
      [
        1776750735520.742,
        0.02387252685549107
      ],
      [
        1776778049069.1292,
        0.024131917019388223
      ],
      [
        1776805362617.516,
        0.023677224932612213
      ]
    ],
    "the-swarm": [
      [
        1776204464553,
        0.0009276114411864995
      ],
      [
        1776233611540.952,
        0.0009303257029610751
      ],
      [
        1776262758528.9036,
        0.0009453898047495278
      ],
      [
        1776291905516.8555,
        0.0009401932853003184
      ],
      [
        1776321052504.8071,
        0.0009531430096613589
      ],
      [
        1776350199492.759,
        0.0009595110805699048
      ],
      [
        1776379346480.711,
        0.0009558739779276403
      ],
      [
        1776408493468.6626,
        0.0009276960061379731
      ],
      [
        1776437640456.6145,
        0.0009634783793013752
      ],
      [
        1776466787444.5662,
        0.0009344725992038558
      ],
      [
        1776495934432.518,
        0.0009276496601476465
      ],
      [
        1776525081420.47,
        0.0009338642514199772
      ],
      [
        1776554228408.4216,
        0.0009327918912351423
      ],
      [
        1776583375396.3735,
        0.0009201819726093335
      ],
      [
        1776612522384.3252,
        0.0009532244324148909
      ],
      [
        1776641669372.277,
        0.0009226747339118428
      ],
      [
        1776670816360.229,
        0.0009286256333316995
      ],
      [
        1776699963348.1807,
        0.0009530555337742134
      ],
      [
        1776729110336.1326,
        0.0009489005097050018
      ],
      [
        1776758257324.0842,
        0.0009399848409732525
      ],
      [
        1776787404312.0361,
        0.0009302230458319211
      ]
    ],
    "otto-ai": [
      [
        1776204464553,
        0.0015871865032181147
      ],
      [
        1776233611540.952,
        0.0015875467293636264
      ],
      [
        1776262758528.9036,
        0.0015996874370425738
      ],
      [
        1776291905516.8555,
        0.0016113033146549368
      ],
      [
        1776321052504.8071,
        0.0016439855732835586
      ],
      [
        1776350199492.759,
        0.0016710973866503696
      ],
      [
        1776379346480.711,
        0.00173144494862867
      ],
      [
        1776408493468.6626,
        0.001685473680135986
      ],
      [
        1776437640456.6145,
        0.0017513443362419247
      ],
      [
        1776466787444.5662,
        0.0018065996033053472
      ],
      [
        1776495934432.518,
        0.001735657888839691
      ],
      [
        1776525081420.47,
        0.0015852781906791984
      ],
      [
        1776554228408.4216,
        0.0012486848066663137
      ],
      [
        1776583375396.3735,
        0.001179535833757195
      ],
      [
        1776612522384.3252,
        0.00117926935777446
      ],
      [
        1776641669372.277,
        0.0011285824266946461
      ],
      [
        1776670816360.229,
        0.001128687224048314
      ],
      [
        1776699963348.1807,
        0.001154644364082999
      ],
      [
        1776729110336.1326,
        0.001140185809860264
      ],
      [
        1776758257324.0842,
        0.0011262171689577242
      ],
      [
        1776787404312.0361,
        0.0011171008914383218
      ]
    ],
    "orbofi-ai": [
      [
        1776204464554,
        0.0004144742372414116
      ],
      [
        1776233611541.952,
        0.0004355518454427873
      ],
      [
        1776262758529.9036,
        0.00043065947010880666
      ],
      [
        1776291905517.8555,
        0.0004235873758578902
      ],
      [
        1776321052505.8071,
        0.00040838410928419164
      ],
      [
        1776350199493.759,
        0.000421605759261905
      ],
      [
        1776379346481.711,
        0.00041894596849735495
      ],
      [
        1776408493469.6626,
        0.00042137540126190205
      ],
      [
        1776437640457.6145,
        0.0004474537657647721
      ],
      [
        1776466787445.5662,
        0.00045517949121998044
      ],
      [
        1776495934433.518,
        0.00045908614315850186
      ],
      [
        1776525081421.47,
        0.00045016783029713727
      ],
      [
        1776554228409.4216,
        0.0004522363263263727
      ],
      [
        1776583375397.3735,
        0.0004218404677995593
      ],
      [
        1776612522385.3252,
        0.000408363974260403
      ],
      [
        1776641669373.277,
        0.00040180091522481223
      ],
      [
        1776670816361.229,
        0.0004077136470562945
      ],
      [
        1776699963349.1807,
        0.00039783604343608594
      ],
      [
        1776729110337.1326,
        0.0003671828598721233
      ],
      [
        1776758257325.0842,
        0.00037586204708925814
      ],
      [
        1776787404313.0361,
        0.0003668949621427025
      ]
    ],
    "gloria-ai": [
      [
        1776204464554,
        0.0005381765524027692
      ],
      [
        1776234070148.4055,
        0.0005426094580908876
      ],
      [
        1776263675742.8113,
        0.0005418500489004245
      ],
      [
        1776293281337.2168,
        0.00054533081294113
      ],
      [
        1776322886931.6223,
        0.000561846733280409
      ],
      [
        1776352492526.028,
        0.0005704327351469807
      ],
      [
        1776382098120.4336,
        0.0005723653671629097
      ],
      [
        1776411703714.839,
        0.0005875642973598535
      ],
      [
        1776441309309.2449,
        0.0005708339319585084
      ],
      [
        1776470914903.6504,
        0.0006305663979723786
      ],
      [
        1776500520498.056,
        0.0006067122310125683
      ],
      [
        1776530126092.4614,
        0.000597352389976798
      ],
      [
        1776559731686.8672,
        0.0005804928887203437
      ],
      [
        1776589337281.2727,
        0.0005739903218796222
      ],
      [
        1776618942875.6782,
        0.000567667026325011
      ],
      [
        1776648548470.084,
        0.0005562293862209613
      ],
      [
        1776678154064.4895,
        0.0005632123835315087
      ],
      [
        1776707759658.895,
        0.0005479689404244677
      ],
      [
        1776737365253.3008,
        0.0005481777090377451
      ],
      [
        1776766970847.7063,
        0.0005595807897317428
      ],
      [
        1776796576442.1118,
        0.0005603457185200308
      ]
    ],
    "prxvt-by-virtuals": [
      [
        1776204464554,
        0.0007539118023366739
      ],
      [
        1776233611541.952,
        0.0007545239655626966
      ],
      [
        1776262758529.9036,
        0.0007179468750553885
      ],
      [
        1776291905517.8555,
        0.0007737538264161826
      ],
      [
        1776321052505.8071,
        0.0009225568152397775
      ],
      [
        1776350199493.759,
        0.0008698061196460954
      ],
      [
        1776379346481.711,
        0.0008863604531026865
      ],
      [
        1776408493469.6626,
        0.0008180153886634267
      ],
      [
        1776437640457.6145,
        0.0008541877345470563
      ],
      [
        1776466787445.5662,
        0.0008042590054263874
      ],
      [
        1776495934433.518,
        0.0007765127489053116
      ],
      [
        1776525081421.47,
        0.0007279872760915507
      ],
      [
        1776554228409.4216,
        0.0008326849801186353
      ],
      [
        1776583375397.3735,
        0.0007852528432014513
      ],
      [
        1776612522385.3252,
        0.0008072397663874122
      ],
      [
        1776641669373.277,
        0.0007710572838696784
      ],
      [
        1776670816361.229,
        0.0007694396934424556
      ],
      [
        1776699963349.1807,
        0.0007911413594876952
      ],
      [
        1776729110337.1326,
        0.0006358298136476166
      ],
      [
        1776758257325.0842,
        0.0006596303642296421
      ],
      [
        1776787404313.0361,
        0.000663106413806749
      ]
    ],
    "neurobro": [
      [
        1776204464554,
        0.0005106692767490747
      ],
      [
        1776233611541.952,
        0.0005085847809192647
      ],
      [
        1776262758529.9036,
        0.0005249593761943121
      ],
      [
        1776291905517.8555,
        0.0005013432245987977
      ],
      [
        1776321052505.8071,
        0.0005170681100307428
      ],
      [
        1776350199493.759,
        0.0005273904088497675
      ],
      [
        1776379346481.711,
        0.0005399737574936293
      ],
      [
        1776408493469.6626,
        0.0005273026868003875
      ],
      [
        1776437640457.6145,
        0.0005536821865628258
      ],
      [
        1776466787445.5662,
        0.0005519263616826757
      ],
      [
        1776495934433.518,
        0.0005445058005434209
      ],
      [
        1776525081421.47,
        0.0005271475586596696
      ],
      [
        1776554228409.4216,
        0.0005181111354459425
      ],
      [
        1776583375397.3735,
        0.0005023543500439324
      ],
      [
        1776612522385.3252,
        0.0005160320164076039
      ],
      [
        1776641669373.277,
        0.0004863173329113764
      ],
      [
        1776670816361.229,
        0.0004896874102104072
      ],
      [
        1776699963349.1807,
        0.0005041200286800636
      ],
      [
        1776729110337.1326,
        0.0004966547620182194
      ],
      [
        1776758257325.0842,
        0.0004903677896618365
      ],
      [
        1776787404313.0361,
        0.0004789745181039778
      ]
    ],
    "ace-data-cloud-2": [
      [
        1776204464554,
        0.0004432210201443441
      ],
      [
        1776233611541.952,
        0.0004362873059999864
      ],
      [
        1776262758529.9036,
        0.00042894629178118817
      ],
      [
        1776291905517.8555,
        0.0004509837307316809
      ],
      [
        1776321052505.8071,
        0.000499826631908449
      ],
      [
        1776350199493.759,
        0.0004950693868039634
      ],
      [
        1776379346481.711,
        0.0005145818102910785
      ],
      [
        1776408493469.6626,
        0.0004262361714793541
      ],
      [
        1776437640457.6145,
        0.000438263737799858
      ],
      [
        1776466787445.5662,
        0.0004428374185217667
      ],
      [
        1776495934433.518,
        0.00041599410626576343
      ],
      [
        1776525081421.47,
        0.00040450305868960424
      ],
      [
        1776554228409.4216,
        0.00040274764301479816
      ],
      [
        1776583375397.3735,
        0.00039163108139770664
      ],
      [
        1776612522385.3252,
        0.0003377879784838463
      ],
      [
        1776641669373.277,
        0.000351455641057757
      ],
      [
        1776670816361.229,
        0.0003649309418426601
      ],
      [
        1776699963349.1807,
        0.00036095101591791427
      ],
      [
        1776729110337.1326,
        0.00034337986087391723
      ],
      [
        1776758257325.0842,
        0.0003430853174772845
      ],
      [
        1776787404313.0361,
        0.00035667534824715614
      ]
    ],
    "capminal": [
      [
        1776204464554,
        0.0005006124562184874
      ],
      [
        1776233611541.952,
        0.0005030685724651112
      ],
      [
        1776262758529.9036,
        0.0005152298773438835
      ],
      [
        1776291905517.8555,
        0.0005135836334129592
      ],
      [
        1776321052505.8071,
        0.0005315122201792388
      ],
      [
        1776350199493.759,
        0.0005456965732044453
      ],
      [
        1776379346481.711,
        0.0005764955963651024
      ],
      [
        1776408493469.6626,
        0.0005569512436473436
      ],
      [
        1776437640457.6145,
        0.0005879911831030591
      ],
      [
        1776466787445.5662,
        0.0005801896958682925
      ],
      [
        1776495934433.518,
        0.000568741662235154
      ],
      [
        1776525081421.47,
        0.0005502756110195931
      ],
      [
        1776554228409.4216,
        0.0005388671254179816
      ],
      [
        1776583375397.3735,
        0.0005322129643773466
      ],
      [
        1776612522385.3252,
        0.0005435862478865493
      ],
      [
        1776641669373.277,
        0.0005197860074294888
      ],
      [
        1776670816361.229,
        0.0005184247453721464
      ],
      [
        1776699963349.1807,
        0.0005375615879871789
      ],
      [
        1776729110337.1326,
        0.0005352667404613961
      ],
      [
        1776758257325.0842,
        0.0005176307471907263
      ],
      [
        1776787404313.0361,
        0.0005180262968432595
      ]
    ],
    "smolcoin-2": [
      [
        1776204464554,
        0.0003330791891970804
      ],
      [
        1776229664554,
        0.0003342892152142537
      ],
      [
        1776254864554,
        0.0003387923065344786
      ],
      [
        1776280064554,
        0.00035713161314360875
      ],
      [
        1776305264554,
        0.0003648166476315138
      ],
      [
        1776330464554,
        0.000365499554426418
      ],
      [
        1776355664554,
        0.0003680281177361385
      ],
      [
        1776380864554,
        0.00036839645413036466
      ],
      [
        1776406064554,
        0.000372843326070417
      ],
      [
        1776431264554,
        0.00037651053279468493
      ],
      [
        1776456464554,
        0.0003750431202833574
      ],
      [
        1776481664554,
        0.0003887487107357131
      ],
      [
        1776506864554,
        0.0003834435082188641
      ],
      [
        1776532064554,
        0.00040501972668158416
      ],
      [
        1776557264554,
        0.0003816364478631496
      ],
      [
        1776582464554,
        0.0003752820868145387
      ],
      [
        1776607664554,
        0.00036250637391012336
      ],
      [
        1776632864554,
        0.00036243616413776983
      ],
      [
        1776658064554,
        0.0003509271330480662
      ],
      [
        1776683264554,
        0.00034877480320942914
      ],
      [
        1776708464554,
        0.00035156269582972287
      ],
      [
        1776733664554,
        0.0003528755994409349
      ],
      [
        1776758864554,
        0.00034753077756517216
      ],
      [
        1776784064554,
        0.00033943021484172703
      ]
    ],
    "trackgood-ai": [
      [
        1776204464554,
        0.00032756019930666206
      ],
      [
        1776233611541.952,
        0.0003222145106708928
      ],
      [
        1776262758529.9036,
        0.0003203339526436984
      ],
      [
        1776291905517.8555,
        0.00032469043255201925
      ],
      [
        1776321052505.8071,
        0.0002872958006481525
      ],
      [
        1776350199493.759,
        0.00029148676841251985
      ],
      [
        1776379346481.711,
        0.00027104770323518727
      ],
      [
        1776408493469.6626,
        0.00026194291654777743
      ],
      [
        1776437640457.6145,
        0.0002686928654121099
      ],
      [
        1776466787445.5662,
        0.0002828615156941181
      ],
      [
        1776495934433.518,
        0.000280781699297007
      ],
      [
        1776525081421.47,
        0.0002770047082705113
      ],
      [
        1776554228409.4216,
        0.0002751459027526302
      ],
      [
        1776583375397.3735,
        0.0002748716043276485
      ],
      [
        1776612522385.3252,
        0.000265450196571722
      ],
      [
        1776641669373.277,
        0.00026135401193961726
      ],
      [
        1776670816361.229,
        0.00026831058850839437
      ],
      [
        1776699963349.1807,
        0.0002752877191395943
      ],
      [
        1776729110337.1326,
        0.0002834944869084909
      ],
      [
        1776758257325.0842,
        0.0002811360078079452
      ],
      [
        1776787404313.0361,
        0.0002790462907591871
      ]
    ],
    "zara-ai": [
      [
        1776204464554,
        0.00041979802400825175
      ],
      [
        1776233611541.952,
        0.0004072544337444243
      ],
      [
        1776262758529.9036,
        0.00039326911780060094
      ],
      [
        1776291905517.8555,
        0.0004142731273697501
      ],
      [
        1776321052505.8071,
        0.00040769422733212
      ],
      [
        1776350199493.759,
        0.00039205215200508977
      ],
      [
        1776379346481.711,
        0.0004140724213969803
      ],
      [
        1776408493469.6626,
        0.0004108210695023435
      ],
      [
        1776437640457.6145,
        0.00040946357559442623
      ],
      [
        1776466787445.5662,
        0.000415416891655101
      ],
      [
        1776495934433.518,
        0.00041014733035103985
      ],
      [
        1776525081421.47,
        0.00040570760732615096
      ],
      [
        1776554228409.4216,
        0.000403049805137632
      ],
      [
        1776583375397.3735,
        0.0003960059487473984
      ],
      [
        1776612522385.3252,
        0.0004015154783682196
      ],
      [
        1776641669373.277,
        0.0004232251062178806
      ],
      [
        1776670816361.229,
        0.0004124115275623212
      ],
      [
        1776699963349.1807,
        0.00042299879847107176
      ],
      [
        1776729110337.1326,
        0.0004278463206904398
      ],
      [
        1776758257325.0842,
        0.0004093267249356367
      ],
      [
        1776787404313.0361,
        0.0004113795232375902
      ]
    ],
    "wachxbt": [
      [
        1776204464554,
        0.000413649740020328
      ],
      [
        1776233611541.952,
        0.0004110112236969495
      ],
      [
        1776262758529.9036,
        0.0004209526851251856
      ],
      [
        1776291905517.8555,
        0.0003987744911471466
      ],
      [
        1776321052505.8071,
        0.00042646170286024624
      ],
      [
        1776350199493.759,
        0.00044554142965126073
      ],
      [
        1776379346481.711,
        0.00046048528752187426
      ],
      [
        1776408493469.6626,
        0.00044696163719513835
      ],
      [
        1776437640457.6145,
        0.0004743357616288629
      ],
      [
        1776466787445.5662,
        0.0004541848133835465
      ],
      [
        1776495934433.518,
        0.00045027150484981004
      ],
      [
        1776525081421.47,
        0.0004344240182262444
      ],
      [
        1776554228409.4216,
        0.0004296089320272976
      ],
      [
        1776583375397.3735,
        0.000412218107057163
      ],
      [
        1776612522385.3252,
        0.00041306730229230824
      ],
      [
        1776641669373.277,
        0.0003807843747459741
      ],
      [
        1776670816361.229,
        0.0003796058893709539
      ],
      [
        1776699963349.1807,
        0.0004094117877920502
      ],
      [
        1776729110337.1326,
        0.000407217406104432
      ],
      [
        1776758257325.0842,
        0.0004101799425897114
      ],
      [
        1776787404313.0361,
        0.0003877204017384999
      ]
    ],
    "mio": [
      [
        1776204464554,
        0.00023736223729371007
      ],
      [
        1776231955463.0908,
        0.00023826070713133768
      ],
      [
        1776259446372.182,
        0.00024114656991855172
      ],
      [
        1776286937281.2727,
        0.00024293462689852348
      ],
      [
        1776314428190.3635,
        0.0002400873167465637
      ],
      [
        1776341919099.4546,
        0.00024458357590574506
      ],
      [
        1776369410008.5454,
        0.00024265837366060827
      ],
      [
        1776396900917.6365,
        0.0002561965187690878
      ],
      [
        1776424391826.7273,
        0.0002495696192273401
      ],
      [
        1776451882735.818,
        0.0002466698017296509
      ],
      [
        1776479373644.9092,
        0.00023796159068262068
      ],
      [
        1776506864554,
        0.0002390147983715429
      ],
      [
        1776534355463.0908,
        0.00023459587122627806
      ],
      [
        1776561846372.182,
        0.00023119051295098202
      ],
      [
        1776589337281.2727,
        0.00022743079044094592
      ],
      [
        1776616828190.3635,
        0.00022767393464355592
      ],
      [
        1776644319099.4546,
        0.00022661040719550057
      ],
      [
        1776671810008.5454,
        0.00022584982512060736
      ],
      [
        1776699300917.6365,
        0.00022676969357076935
      ],
      [
        1776726791826.7273,
        0.00022496412610517637
      ],
      [
        1776754282735.818,
        0.00022174100258595187
      ],
      [
        1776781773644.9092,
        0.00022356187308586497
      ]
    ],
    "praxis": [
      [
        1776204464554,
        0.004229625642765263
      ],
      [
        1776233611541.952,
        0.00420056256750175
      ],
      [
        1776262758529.9036,
        0.003954689095174812
      ],
      [
        1776291905517.8555,
        0.004094377154316641
      ],
      [
        1776321052505.8071,
        0.004066141295054318
      ],
      [
        1776350199493.759,
        0.003788647314707976
      ],
      [
        1776379346481.711,
        0.0037153949987626163
      ],
      [
        1776408493469.6626,
        0.0035984639377535073
      ],
      [
        1776437640457.6145,
        0.003523973370535827
      ],
      [
        1776466787445.5662,
        0.0036414142368478447
      ],
      [
        1776495934433.518,
        0.0035362549653669586
      ],
      [
        1776525081421.47,
        0.00269917740576727
      ],
      [
        1776554228409.4216,
        0.0026524200033732994
      ],
      [
        1776583375397.3735,
        0.002659344226598705
      ],
      [
        1776612522385.3252,
        0.002300675704540666
      ],
      [
        1776641669373.277,
        0.0023635980681777436
      ],
      [
        1776670816361.229,
        0.002410548511489944
      ],
      [
        1776699963349.1807,
        0.002361400689339393
      ],
      [
        1776729110337.1326,
        0.0023386642407319173
      ],
      [
        1776758257325.0842,
        0.0023089173039009024
      ],
      [
        1776787404313.0361,
        0.0022433047223082017
      ]
    ],
    "xona-agent": [
      [
        1776204464554,
        0.00019775706106533544
      ],
      [
        1776233611541.952,
        0.00019408156644659414
      ],
      [
        1776262758529.9036,
        0.00019294312205061438
      ],
      [
        1776291905517.8555,
        0.00019438435317483213
      ],
      [
        1776321052505.8071,
        0.00018457627143578944
      ],
      [
        1776350199493.759,
        0.00021348950785366405
      ],
      [
        1776379346481.711,
        0.00021941935566053406
      ],
      [
        1776408493469.6626,
        0.00017978402037841044
      ],
      [
        1776437640457.6145,
        0.000189104348898282
      ],
      [
        1776466787445.5662,
        0.00020577852914283748
      ],
      [
        1776495934433.518,
        0.0001678751104135903
      ],
      [
        1776525081421.47,
        0.00017606356487873427
      ],
      [
        1776554228409.4216,
        0.00018387769789199703
      ],
      [
        1776583375397.3735,
        0.00019515312383435978
      ],
      [
        1776612522385.3252,
        0.00019133737014409197
      ],
      [
        1776641669373.277,
        0.00020329391242384528
      ],
      [
        1776670816361.229,
        0.0002048164727667114
      ],
      [
        1776699963349.1807,
        0.00022359934790596795
      ],
      [
        1776729110337.1326,
        0.00023654860680361587
      ],
      [
        1776758257325.0842,
        0.00020944063136312918
      ],
      [
        1776787404313.0361,
        0.0002012985875387048
      ]
    ],
    "eliza": [
      [
        1776204464555,
        0.0002262832436052436
      ],
      [
        1776233611542.952,
        0.00022338350413972558
      ],
      [
        1776262758530.9036,
        0.00022537966352260735
      ],
      [
        1776291905518.8555,
        0.00022763492680434412
      ],
      [
        1776321052506.8071,
        0.0002277092279454372
      ],
      [
        1776350199494.759,
        0.00023487458824856454
      ],
      [
        1776379346482.711,
        0.0002477142091942208
      ],
      [
        1776408493470.6626,
        0.00024477506783884644
      ],
      [
        1776437640458.6145,
        0.0002468935969499094
      ],
      [
        1776466787446.5662,
        0.00025063519678270404
      ],
      [
        1776495934434.518,
        0.0002222637907855499
      ],
      [
        1776525081422.47,
        0.0002117372711451983
      ],
      [
        1776554228410.4216,
        0.00020929507783873328
      ],
      [
        1776583375398.3735,
        0.00020684153062675467
      ],
      [
        1776612522386.3252,
        0.00020727366406447795
      ],
      [
        1776641669374.277,
        0.00020612311754110758
      ],
      [
        1776670816362.229,
        0.00019954501059608467
      ],
      [
        1776699963350.1807,
        0.0001980824921586081
      ],
      [
        1776729110338.1326,
        0.00020113103739117884
      ],
      [
        1776758257326.0842,
        0.00019810603036667107
      ],
      [
        1776787404314.0361,
        0.00019834323203409771
      ]
    ],
    "regent-2": [
      [
        1776204464555,
        0.000012840504940885424
      ],
      [
        1776231259491.7087,
        0.00001008585550368447
      ],
      [
        1776258054428.4177,
        0.000010257670201942605
      ],
      [
        1776284849365.1265,
        0.000010252815310019938
      ],
      [
        1776311644301.8354,
        0.000010299371439988788
      ],
      [
        1776338439238.5442,
        0.000010225969556668154
      ],
      [
        1776365234175.2532,
        0.000010103475894341134
      ],
      [
        1776392029111.962,
        0.000010067366688713402
      ],
      [
        1776418824048.671,
        0.000010014725985594569
      ],
      [
        1776445618985.3796,
        0.00001007264816232193
      ],
      [
        1776472413922.0886,
        0.000010626663511673875
      ],
      [
        1776499208858.7974,
        0.000010085463071739338
      ],
      [
        1776526003795.5063,
        0.000009540604151381055
      ],
      [
        1776552798732.215,
        0.000009740710634277123
      ],
      [
        1776579593668.924,
        0.00000956257665733434
      ],
      [
        1776606388605.6328,
        0.000009435807720439116
      ],
      [
        1776633183542.3418,
        0.000009522916747142894
      ],
      [
        1776659978479.0505,
        0.000009284577780493035
      ],
      [
        1776686773415.7595,
        0.00000937408287907437
      ],
      [
        1776713568352.4683,
        0.000009615040062360795
      ],
      [
        1776740363289.1772,
        0.000009747320619013349
      ],
      [
        1776767158225.886,
        0.000009693138230458965
      ],
      [
        1776793953162.595,
        0.000009674098386720555
      ]
    ],
    "kilt-protocol-3": [
      [
        1776204464555,
        0.00046079733977606843
      ],
      [
        1776233611542.952,
        0.0004687431647128064
      ],
      [
        1776262758530.9036,
        0.0004688153053441772
      ],
      [
        1776291905518.8555,
        0.000506862274908344
      ],
      [
        1776321052506.8071,
        0.0005033747896696294
      ],
      [
        1776350199494.759,
        0.0005661068262922676
      ],
      [
        1776379346482.711,
        0.0007048657122135581
      ],
      [
        1776408493470.6626,
        0.0005672304086810946
      ],
      [
        1776437640458.6145,
        0.0005767655904973803
      ],
      [
        1776466787446.5662,
        0.0005836255374528512
      ],
      [
        1776495934434.518,
        0.0005841332293436997
      ],
      [
        1776525081422.47,
        0.0006409945736433612
      ],
      [
        1776554228410.4216,
        0.0006376731687554789
      ],
      [
        1776583375398.3735,
        0.0006399923447683322
      ],
      [
        1776612522386.3252,
        0.0006353184146080768
      ],
      [
        1776641669374.277,
        0.0006225717051731122
      ],
      [
        1776670816362.229,
        0.0006209091438204946
      ],
      [
        1776699963350.1807,
        0.0006385630809922909
      ],
      [
        1776729110338.1326,
        0.0006415455258493075
      ],
      [
        1776758257326.0842,
        0.0006359561404947879
      ],
      [
        1776787404314.0361,
        0.0006008134295258373
      ]
    ],
    "hey-lol": [
      [
        1776204464555,
        0.0006023671883140418
      ],
      [
        1776233611542.952,
        0.0005685508215816119
      ],
      [
        1776262758530.9036,
        0.000567215259711912
      ],
      [
        1776291905518.8555,
        0.0005239875102469004
      ],
      [
        1776321052506.8071,
        0.000502535376214241
      ],
      [
        1776350199494.759,
        0.0005206607108848671
      ],
      [
        1776379346482.711,
        0.0005737616637107935
      ],
      [
        1776408493470.6626,
        0.0005524620314715073
      ],
      [
        1776437640458.6145,
        0.0005428949890086206
      ],
      [
        1776466787446.5662,
        0.0005285936020650715
      ],
      [
        1776495934434.518,
        0.0005299832180068753
      ],
      [
        1776525081422.47,
        0.0004871448400677475
      ],
      [
        1776554228410.4216,
        0.000493451031979417
      ],
      [
        1776583375398.3735,
        0.000475861895082541
      ],
      [
        1776612522386.3252,
        0.0004878229320998491
      ],
      [
        1776641669374.277,
        0.0004804411638113859
      ],
      [
        1776670816362.229,
        0.00048197539861114457
      ],
      [
        1776699963350.1807,
        0.0004893985942428738
      ],
      [
        1776729110338.1326,
        0.0004884608276715444
      ],
      [
        1776758257326.0842,
        0.0004986004161332127
      ],
      [
        1776787404314.0361,
        0.0005009304818465644
      ]
    ],
    "token-metrics-ai": [
      [
        1776204464555,
        0.000020056095177914855
      ],
      [
        1776233611542.952,
        0.000018566767318598893
      ],
      [
        1776262758530.9036,
        0.000027555878533768655
      ],
      [
        1776291905518.8555,
        0.000023263569468144302
      ],
      [
        1776321052506.8071,
        0.000022196520317371717
      ],
      [
        1776350199494.759,
        0.0000212340259663647
      ],
      [
        1776379346482.711,
        0.000025755204006220808
      ],
      [
        1776408493470.6626,
        0.000024719709686685058
      ],
      [
        1776437640458.6145,
        0.000023040491794434464
      ],
      [
        1776466787446.5662,
        0.000026193095660619486
      ],
      [
        1776495934434.518,
        0.000024804855437856322
      ],
      [
        1776525081422.47,
        0.000025703047197186647
      ],
      [
        1776554228410.4216,
        0.000023060706113061833
      ],
      [
        1776583375398.3735,
        0.000024913221375811942
      ],
      [
        1776612522386.3252,
        0.000022511365345257375
      ],
      [
        1776641669374.277,
        0.000024366960791068738
      ],
      [
        1776670816362.229,
        0.000022382244005898467
      ],
      [
        1776699963350.1807,
        0.000024501044971315017
      ],
      [
        1776729110338.1326,
        0.000022609721607876327
      ],
      [
        1776758257326.0842,
        0.000022542246427686713
      ],
      [
        1776787404314.0361,
        0.00002148436341063257
      ]
    ],
    "x4pay": [
      [
        1776204464555,
        0.00001873896840915031
      ],
      [
        1776232877977.8188,
        0.000018801073647411786
      ],
      [
        1776261291400.6377,
        0.00001921852205278732
      ],
      [
        1776289704823.4563,
        0.000019414453215557688
      ],
      [
        1776318118246.2751,
        0.000019400490100153953
      ],
      [
        1776346531669.094,
        0.000019834622665108026
      ],
      [
        1776374945091.9128,
        0.00002103005054003486
      ],
      [
        1776403358514.7314,
        0.000021879288353297635
      ],
      [
        1776431771937.5503,
        0.00002174035175896635
      ],
      [
        1776460185360.3691,
        0.000021768969057753488
      ],
      [
        1776488598783.188,
        0.0000210794929710839
      ],
      [
        1776517012206.0066,
        0.000020954793270814193
      ],
      [
        1776545425628.8254,
        0.00002076826145707683
      ],
      [
        1776573839051.6443,
        0.000020926343338560798
      ],
      [
        1776602252474.4631,
        0.000021725117162581513
      ],
      [
        1776630665897.282,
        0.000021009652947515512
      ],
      [
        1776659079320.1006,
        0.00002099736515298452
      ],
      [
        1776687492742.9194,
        0.000021246675111922074
      ],
      [
        1776715906165.7383,
        0.000021533989777496415
      ],
      [
        1776744319588.5571,
        0.00002081612953181803
      ],
      [
        1776772733011.3757,
        0.00002101612373222056
      ],
      [
        1776801146434.1946,
        0.000020489063891319806
      ]
    ],
    "x402jobs": [
      [
        1776204464555,
        0.000010917579349829857
      ],
      [
        1776233264555,
        0.000010780791119011059
      ],
      [
        1776262064555,
        0.000010680659545991373
      ],
      [
        1776290864555,
        0.000010844479728598268
      ],
      [
        1776319664555,
        0.000010897023194232494
      ],
      [
        1776348464555,
        0.000010897023194232494
      ],
      [
        1776377264555,
        0.00001130378185668621
      ],
      [
        1776406064555,
        0.000011423765156075599
      ],
      [
        1776434864555,
        0.000011681204033078261
      ],
      [
        1776463664555,
        0.000011699736013125275
      ],
      [
        1776492464555,
        0.00001148757093392294
      ],
      [
        1776521264555,
        0.000011276328149703054
      ],
      [
        1776550064555,
        0.000011172840039809493
      ],
      [
        1776578864555,
        0.00001121287409903281
      ],
      [
        1776607664555,
        0.000011323523111242945
      ],
      [
        1776636464555,
        0.000011403376677525172
      ],
      [
        1776665264555,
        0.000011549992450481406
      ],
      [
        1776694064555,
        0.000011547088837999524
      ],
      [
        1776722864555,
        0.000011666408955767105
      ],
      [
        1776751664555,
        0.000011795447575458429
      ],
      [
        1776780464555,
        0.00001195461577735909
      ]
    ],
    "agentbank-x402-protocol": [
      [
        1776204464555,
        0.000004529835212453122
      ],
      [
        1776271664555,
        0.0000045610226727009826
      ],
      [
        1776338864555,
        0.000004579791429559341
      ],
      [
        1776406064555,
        0.000004602919062428437
      ],
      [
        1776473264555,
        0.000004573350408724816
      ],
      [
        1776540464555,
        0.000004550120117980959
      ],
      [
        1776607664555,
        0.000004548641708048974
      ],
      [
        1776674864555,
        0.0000046022240345214135
      ],
      [
        1776742064555,
        0.0000046579466607737275
      ]
    ],
    "sol402-proxy": [
      [
        1776204464555,
        0.0000029296329680214566
      ],
      [
        1776238064555,
        0.0000029502570936322098
      ],
      [
        1776271664555,
        0.000002933674233689676
      ],
      [
        1776305264555,
        0.0000029384307024359106
      ],
      [
        1776338864555,
        0.000002959331981321172
      ],
      [
        1776372464555,
        0.000002959331981321172
      ],
      [
        1776406064555,
        0.0000029490681363744414
      ],
      [
        1776439664555,
        0.00000298778554372883
      ],
      [
        1776473264555,
        0.0000029747169869820268
      ],
      [
        1776506864555,
        0.000003011475911842036
      ],
      [
        1776540464555,
        0.0000030192206425388916
      ],
      [
        1776574064555,
        0.0000030182510819333
      ],
      [
        1776607664555,
        0.0000029833347522712303
      ],
      [
        1776641264555,
        0.0000030046083395736974
      ],
      [
        1776674864555,
        0.000003019587609346784
      ],
      [
        1776708464555,
        0.000002990145189059013
      ],
      [
        1776742064555,
        0.0000030033263217382076
      ],
      [
        1776775664555,
        0.0000029993424359822686
      ]
    ],
    "bridge402": []
  },
  "updated": "2026-04-21T22:07:44.555Z"
}